ASCII/__init__.py
ASCII/core/encoded_files.cp311-win_amd64.pyd
ascii25-0.2.2.dist-info/METADATA
ascii25-0.2.2.dist-info/WHEEL
ascii25-0.2.2.dist-info/top_level.txt
ascii25-0.2.2.dist-info/RECORD
